securityLayer/AccessControl.py
securityLayer/AuthAnswer.py
securityLayer/Error.py
securityLayer/SSO.py
securityLayer/SecurityLayer.py
securityLayer/__init__.py
securityLayer/default.py
d20_securityLayer-1.0.0.dist-info/LICENSE
d20_securityLayer-1.0.0.dist-info/METADATA
d20_securityLayer-1.0.0.dist-info/WHEEL
d20_securityLayer-1.0.0.dist-info/top_level.txt
d20_securityLayer-1.0.0.dist-info/RECORD
