Metadata-Version: 2.1
Name: d20-securityLayer
Version: 1.0.0
Summary: A simple access manager
Home-page: https://github.com/d20services/security_layer_python_arangodb
Author: Alex Sánchez Vega
Author-email: alex@d20.services
License: UNKNOWN
Project-URL: Bug Tracker, https://github.com/d20services/security_layer_python_arangodb/issues
Platform: UNKNOWN
Classifier: Programming Language :: Python :: 3
Classifier: License :: OSI Approved :: MIT License
Classifier: Operating System :: OS Independent
Requires-Python: >=3.8
License-File: LICENSE
Requires-Dist: pyArango
Requires-Dist: datetime
Requires-Dist: d20-orm
Requires-Dist: cryptography
Requires-Dist: flask
Requires-Dist: d20-communications
